{"map":[[{"col":0,"gridData":{"color":{"a":0,"b":0,"g":0,"r":0},"colorId":0,"depth":0,"index":0},"row":0},{"col":0,"gridData":{"color":{"a":0,"b":0,"g":0,"r":0},"colorId":0,"depth":0,"index":0},"row":1},{"col":0,"gridData":{"color":{"a":0,"b":0,"g":0,"r":0},"colorId":0,"depth":0,"index":0},"row":2},{"col":0,"gridData":{"color":{"a":0,"b":0,"g":0,"r":0},"colorId":0,"depth":0,"index":0},"row":3},{"col":0,"gridData":{"color":{"a":0,"b":0,"g":0,"r":0},"colorId":0,"depth":0,"index":0},"row":4},{"col":0,"gridData":{"color":{"a":0,"b":0,"g":0,"r":0},"colorId":0,"depth":0,"index":0},"row":5},{"col":0,"gridData":{"color":{"a":0,"b":0,"g":0,"r":0},"colorId":0,"depth":0,"index":0},"row":6},{"col":0,"gridData":{"color":{"a":0,"b":0,"g":0,"r":0},"colorId":0,"depth":0,"index":0},"row":7},{"col":0,"gridData":{"color":{"a":0,"b":0,"g":0,"r":0},"colorId":0,"depth":0,"index":0},"row":8},{"col":0,"gridData":{"color":{"a":0,"b":0,"g":0,"r":0},"colorId":0,"depth":0,"index":0},"row":9},{"col":0,"gridData":{"color":{"a":0,"b":0,"g":0,"r":0},"colorId":0,"depth":0,"index":0},"row":10},{"col":0,"gridData":{"color":{"a":0,"b":0,"g":0,"r":0},"colorId":0,"depth":0,"index":0},"row":11},{"col":0,"gridData":{"color":{"a":0,"b":0,"g":0,"r":0},"colorId":0,"depth":0,"index":0},"row":12},{"col":0,"gridData":{"color":{"a":0,"b":0,"g":0,"r":0},"colorId":0,"depth":0,"index":0},"row":13},{"col":0,"gridData":{"color":{"a":0,"b":0,"g":0,"r":0},"colorId":0,"depth":0,"index":0},"row":14},{"col":0,"gridData":{"color":{"a":0,"b":0,"g":0,"r":0},"colorId":0,"depth":0,"index":0},"row":15}],[{"col":1,"gridData":{"color":{"a":0,"b":0,"g":0,"r":0},"colorId":0,"depth":0,"index":0},"row":0},{"col":1,"gridData":{"color":{"a":0,"b":0,"g":0,"r":0},"colorId":0,"depth":0,"index":0},"row":1},{"col":1,"gridData":{"color":{"a":0,"b":0,"g":0,"r":0},"colorId":0,"depth":0,"index":0},"row":2},{"col":1,"gridData":{"color":{"a":0,"b":0,"g":0,"r":0},"colorId":0,"depth":0,"index":0},"row":3},{"col":1,"gridData":{"color":{"a":0,"b":0,"g":0,"r":0},"colorId":0,"depth":0,"index":0},"row":4},{"col":1,"gridData":{"color":{"a":0,"b":0,"g":0,"r":0},"colorId":0,"depth":0,"index":0},"row":5},{"col":1,"gridData":{"color":{"a":0,"b":0,"g":0,"r":0},"colorId":0,"depth":0,"index":0},"row":6},{"col":1,"gridData":{"color":{"a":0,"b":0,"g":0,"r":0},"colorId":0,"depth":0,"index":0},"row":7},{"col":1,"gridData":{"color":{"a":0,"b":0,"g":0,"r":0},"colorId":0,"depth":0,"index":0},"row":8},{"col":1,"gridData":{"color":{"a":0,"b":0,"g":0,"r":0},"colorId":0,"depth":0,"index":0},"row":9},{"col":1,"gridData":{"color":{"a":0,"b":0,"g":0,"r":0},"colorId":0,"depth":0,"index":0},"row":10},{"col":1,"gridData":{"color":{"a":0,"b":0,"g":0,"r":0},"colorId":0,"depth":0,"index":0},"row":11},{"col":1,"gridData":{"color":{"a":0,"b":0,"g":0,"r":0},"colorId":0,"depth":0,"index":0},"row":12},{"col":1,"gridData":{"color":{"a":0,"b":0,"g":0,"r":0},"colorId":0,"depth":0,"index":0},"row":13},{"col":1,"gridData":{"color":{"a":0,"b":0,"g":0,"r":0},"colorId":0,"depth":0,"index":0},"row":14},{"col":1,"gridData":{"color":{"a":0,"b":0,"g":0,"r":0},"colorId":0,"depth":0,"index":0},"row":15}],[{"col":2,"gridData":{"color":{"a":0,"b":0,"g":0,"r":0},"colorId":0,"depth":0,"index":0},"row":0},{"col":2,"gridData":{"color":{"a":0,"b":0,"g":0,"r":0},"colorId":0,"depth":0,"index":0},"row":1},{"col":2,"gridData":{"color":{"a":0,"b":0,"g":0,"r":0},"colorId":0,"depth":0,"index":0},"row":2},{"col":2,"gridData":{"color":{"a":0,"b":0,"g":0,"r":0},"colorId":0,"depth":0,"index":0},"row":3},{"col":2,"gridData":{"color":{"a":0,"b":0,"g":0,"r":0},"colorId":0,"depth":0,"index":0},"row":4},{"col":2,"gridData":{"color":{"a":0,"b":0,"g":0,"r":0},"colorId":0,"depth":0,"index":0},"row":5},{"col":2,"gridData":{"color":{"a":0,"b":0,"g":0,"r":0},"colorId":0,"depth":0,"index":0},"row":6},{"col":2,"gridData":{"color":{"a":0,"b":0,"g":0,"r":0},"colorId":0,"depth":0,"index":0},"row":7},{"col":2,"gridData":{"color":{"a":0,"b":0,"g":0,"r":0},"colorId":0,"depth":0,"index":0},"row":8},{"col":2,"gridData":{"color":{"a":0,"b":0,"g":0,"r":0},"colorId":0,"depth":0,"index":0},"row":9},{"col":2,"gridData":{"color":{"a":0,"b":0,"g":0,"r":0},"colorId":0,"depth":0,"index":0},"row":10},{"col":2,"gridData":{"color":{"a":0,"b":0,"g":0,"r":0},"colorId":0,"depth":0,"index":0},"row":11},{"col":2,"gridData":{"color":{"a":0,"b":0,"g":0,"r":0},"colorId":0,"depth":0,"index":0},"row":12},{"col":2,"gridData":{"color":{"a":0,"b":0,"g":0,"r":0},"colorId":0,"depth":0,"index":0},"row":13},{"col":2,"gridData":{"color":{"a":0,"b":0,"g":0,"r":0},"colorId":0,"depth":0,"index":0},"row":14},{"col":2,"gridData":{"color":{"a":0,"b":0,"g":0,"r":0},"colorId":0,"depth":0,"index":0},"row":15}],[{"col":3,"gridData":{"color":{"a":0,"b":0,"g":0,"r":0},"colorId":0,"depth":0,"index":0},"row":0},{"col":3,"gridData":{"color":{"a":0,"b":0,"g":0,"r":0},"colorId":0,"depth":0,"index":0},"row":1},{"col":3,"gridData":{"color":{"a":0,"b":0,"g":0,"r":0},"colorId":0,"depth":0,"index":0},"row":2},{"col":3,"gridData":{"color":{"a":0,"b":0,"g":0,"r":0},"colorId":0,"depth":0,"index":0},"row":3},{"col":3,"gridData":{"color":{"a":0,"b":0,"g":0,"r":0},"colorId":0,"depth":0,"index":0},"row":4},{"col":3,"gridData":{"color":{"a":0,"b":0,"g":0,"r":0},"colorId":0,"depth":0,"index":0},"row":5},{"col":3,"gridData":{"color":{"a":0,"b":0,"g":0,"r":0},"colorId":0,"depth":0,"index":0},"row":6},{"col":3,"gridData":{"color":{"a":0,"b":0,"g":0,"r":0},"colorId":0,"depth":0,"index":0},"row":7},{"col":3,"gridData":{"color":{"a":0,"b":0,"g":0,"r":0},"colorId":0,"depth":0,"index":0},"row":8},{"col":3,"gridData":{"color":{"a":0,"b":0,"g":0,"r":0},"colorId":0,"depth":0,"index":0},"row":9},{"col":3,"gridData":{"color":{"a":0,"b":0,"g":0,"r":0},"colorId":0,"depth":0,"index":0},"row":10},{"col":3,"gridData":{"color":{"a":0,"b":0,"g":0,"r":0},"colorId":0,"depth":0,"index":0},"row":11},{"col":3,"gridData":{"color":{"a":0,"b":0,"g":0,"r":0},"colorId":0,"depth":0,"index":0},"row":12},{"col":3,"gridData":{"color":{"a":0,"b":0,"g":0,"r":0},"colorId":0,"depth":0,"index":0},"row":13},{"col":3,"gridData":{"color":{"a":0,"b":0,"g":0,"r":0},"colorId":0,"depth":0,"index":0},"row":14},{"col":3,"gridData":{"color":{"a":0,"b":0,"g":0,"r":0},"colorId":0,"depth":0,"index":0},"row":15}],[{"col":4,"gridData":{"color":{"a":0,"b":0,"g":0,"r":0},"colorId":0,"depth":0,"index":0},"row":0},{"col":4,"gridData":{"color":{"a":0,"b":0,"g":0,"r":0},"colorId":0,"depth":0,"index":0},"row":1},{"col":4,"gridData":{"color":{"a":0,"b":0,"g":0,"r":0},"colorId":0,"depth":0,"index":0},"row":2},{"col":4,"gridData":{"color":{"a":0,"b":0,"g":0,"r":0},"colorId":9,"depth":0,"index":0},"row":3},{"col":4,"gridData":{"color":{"a":1,"b":0.5529412,"g":0.7333333,"r":0.9686275},"colorId":9,"depth":2,"index":0},"row":4},{"col":4,"gridData":{"color":{"a":1,"b":0.5529412,"g":0.7333333,"r":0.9686275},"colorId":9,"depth":2,"index":0},"row":5},{"col":4,"gridData":{"color":{"a":1,"b":0.2196078,"g":0.04705882,"r":0.572549},"colorId":0,"depth":3,"index":0},"row":6},{"col":4,"gridData":{"color":{"a":1,"b":0.2196078,"g":0.04705882,"r":0.572549},"colorId":0,"depth":3,"index":0},"row":7},{"col":4,"gridData":{"color":{"a":1,"b":0.2196078,"g":0.04705882,"r":0.572549},"colorId":0,"depth":3,"index":0},"row":8},{"col":4,"gridData":{"color":{"a":0,"b":0,"g":0,"r":0},"colorId":0,"depth":0,"index":0},"row":9},{"col":4,"gridData":{"color":{"a":0,"b":0,"g":0,"r":0},"colorId":0,"depth":0,"index":0},"row":10},{"col":4,"gridData":{"color":{"a":0,"b":0,"g":0,"r":0},"colorId":0,"depth":0,"index":0},"row":11},{"col":4,"gridData":{"color":{"a":0,"b":0,"g":0,"r":0},"colorId":0,"depth":0,"index":0},"row":12},{"col":4,"gridData":{"color":{"a":0,"b":0,"g":0,"r":0},"colorId":0,"depth":0,"index":0},"row":13},{"col":4,"gridData":{"color":{"a":0,"b":0,"g":0,"r":0},"colorId":0,"depth":0,"index":0},"row":14},{"col":4,"gridData":{"color":{"a":0,"b":0,"g":0,"r":0},"colorId":0,"depth":0,"index":0},"row":15}],[{"col":5,"gridData":{"color":{"a":0,"b":0,"g":0,"r":0},"colorId":0,"depth":0,"index":0},"row":0},{"col":5,"gridData":{"color":{"a":0,"b":0,"g":0,"r":0},"colorId":0,"depth":0,"index":0},"row":1},{"col":5,"gridData":{"color":{"a":0,"b":0,"g":0,"r":0},"colorId":0,"depth":0,"index":0},"row":2},{"col":5,"gridData":{"color":{"a":0,"b":0,"g":0,"r":0},"colorId":9,"depth":0,"index":0},"row":3},{"col":5,"gridData":{"color":{"a":1,"b":0.5529412,"g":0.7333333,"r":0.9686275},"colorId":9,"depth":2,"index":0},"row":4},{"col":5,"gridData":{"color":{"a":1,"b":0.5529412,"g":0.7333333,"r":0.9686275},"colorId":9,"depth":3,"index":0},"row":5},{"col":5,"gridData":{"color":{"a":1,"b":0.2196078,"g":0.04705882,"r":0.572549},"colorId":0,"depth":3,"index":0},"row":6},{"col":5,"gridData":{"color":{"a":1,"b":0.2196078,"g":0.04705882,"r":0.572549},"colorId":0,"depth":3,"index":0},"row":7},{"col":5,"gridData":{"color":{"a":1,"b":0.2196078,"g":0.04705882,"r":0.572549},"colorId":0,"depth":3,"index":0},"row":8},{"col":5,"gridData":{"color":{"a":1,"b":0.2196078,"g":0.04705882,"r":0.572549},"colorId":0,"depth":3,"index":0},"row":9},{"col":5,"gridData":{"color":{"a":0,"b":0,"g":0,"r":0},"colorId":0,"depth":0,"index":0},"row":10},{"col":5,"gridData":{"color":{"a":1,"b":0.3254902,"g":0.4901961,"r":0.8313726},"colorId":8,"depth":1,"index":0},"row":11},{"col":5,"gridData":{"color":{"a":0,"b":0,"g":0,"r":0},"colorId":0,"depth":0,"index":0},"row":12},{"col":5,"gridData":{"color":{"a":0,"b":0,"g":0,"r":0},"colorId":0,"depth":0,"index":0},"row":13},{"col":5,"gridData":{"color":{"a":0,"b":0,"g":0,"r":0},"colorId":0,"depth":0,"index":0},"row":14},{"col":5,"gridData":{"color":{"a":0,"b":0,"g":0,"r":0},"colorId":0,"depth":0,"index":0},"row":15}],[{"col":6,"gridData":{"color":{"a":0,"b":0,"g":0,"r":0},"colorId":10,"depth":0,"index":0},"row":0},{"col":6,"gridData":{"color":{"a":1,"b":0.2078431,"g":0.3019608,"r":0.5686275},"colorId":10,"depth":3,"index":0},"row":1},{"col":6,"gridData":{"color":{"a":1,"b":0.8196079,"g":0.7215686,"r":0.6313726},"colorId":5,"depth":2,"index":0},"row":2},{"col":6,"gridData":{"color":{"a":1,"b":0.8196079,"g":0.7215686,"r":0.6313726},"colorId":5,"depth":2,"index":0},"row":3},{"col":6,"gridData":{"color":{"a":1,"b":0.8196079,"g":0.7215686,"r":0.6313726},"colorId":5,"depth":2,"index":0},"row":4},{"col":6,"gridData":{"color":{"a":1,"b":0.2078431,"g":0.3019608,"r":0.5686275},"colorId":10,"depth":3,"index":0},"row":5},{"col":6,"gridData":{"color":{"a":1,"b":0.3333333,"g":0.1647059,"r":0.9137255},"colorId":1,"depth":3,"index":0},"row":6},{"col":6,"gridData":{"color":{"a":1,"b":0.3333333,"g":0.1647059,"r":0.9137255},"colorId":1,"depth":3,"index":0},"row":7},{"col":6,"gridData":{"color":{"a":1,"b":0.3333333,"g":0.1647059,"r":0.9137255},"colorId":1,"depth":3,"index":0},"row":8},{"col":6,"gridData":{"color":{"a":1,"b":0.3333333,"g":0.1647059,"r":0.9137255},"colorId":1,"depth":3,"index":0},"row":9},{"col":6,"gridData":{"color":{"a":1,"b":0.5529412,"g":0.7333333,"r":0.9686275},"colorId":9,"depth":4,"index":0},"row":10},{"col":6,"gridData":{"color":{"a":1,"b":0.5529412,"g":0.7333333,"r":0.9686275},"colorId":9,"depth":4,"index":0},"row":11},{"col":6,"gridData":{"color":{"a":1,"b":0.2078431,"g":0.3019608,"r":0.5686275},"colorId":10,"depth":4,"index":0},"row":12},{"col":6,"gridData":{"color":{"a":1,"b":0.2078431,"g":0.3019608,"r":0.5686275},"colorId":10,"depth":4,"index":0},"row":13},{"col":6,"gridData":{"color":{"a":0,"b":0,"g":0,"r":0},"colorId":0,"depth":0,"index":0},"row":14},{"col":6,"gridData":{"color":{"a":0,"b":0,"g":0,"r":0},"colorId":0,"depth":0,"index":0},"row":15}],[{"col":7,"gridData":{"color":{"a":0,"b":0,"g":0,"r":0},"colorId":0,"depth":0,"index":0},"row":0},{"col":7,"gridData":{"color":{"a":0,"b":0,"g":0,"r":0},"colorId":0,"depth":0,"index":0},"row":1},{"col":7,"gridData":{"color":{"a":0,"b":0,"g":0,"r":0},"colorId":0,"depth":0,"index":0},"row":2},{"col":7,"gridData":{"color":{"a":0,"b":0,"g":0,"r":0},"colorId":0,"depth":0,"index":0},"row":3},{"col":7,"gridData":{"color":{"a":1,"b":0.8196079,"g":0.7215686,"r":0.6313726},"colorId":5,"depth":2,"index":0},"row":4},{"col":7,"gridData":{"color":{"a":1,"b":0.2078431,"g":0.3019608,"r":0.5686275},"colorId":10,"depth":3,"index":0},"row":5},{"col":7,"gridData":{"color":{"a":1,"b":0.8196079,"g":0.7215686,"r":0.6313726},"colorId":5,"depth":3,"index":0},"row":6},{"col":7,"gridData":{"color":{"a":1,"b":0.8196079,"g":0.7215686,"r":0.6313726},"colorId":5,"depth":3,"index":0},"row":7},{"col":7,"gridData":{"color":{"a":1,"b":0.8196079,"g":0.7215686,"r":0.6313726},"colorId":5,"depth":3,"index":0},"row":8},{"col":7,"gridData":{"color":{"a":1,"b":0.3254902,"g":0.4901961,"r":0.8313726},"colorId":8,"depth":3,"index":0},"row":9},{"col":7,"gridData":{"color":{"a":1,"b":0.5529412,"g":0.7333333,"r":0.9686275},"colorId":9,"depth":4,"index":0},"row":10},{"col":7,"gridData":{"color":{"a":1,"b":0.5529412,"g":0.7333333,"r":0.9686275},"colorId":9,"depth":4,"index":0},"row":11},{"col":7,"gridData":{"color":{"a":1,"b":0.5529412,"g":0.7333333,"r":0.9686275},"colorId":9,"depth":4,"index":0},"row":12},{"col":7,"gridData":{"color":{"a":1,"b":0.2078431,"g":0.3019608,"r":0.5686275},"colorId":10,"depth":4,"index":0},"row":13},{"col":7,"gridData":{"color":{"a":0,"b":0,"g":0,"r":0},"colorId":0,"depth":0,"index":0},"row":14},{"col":7,"gridData":{"color":{"a":0,"b":0,"g":0,"r":0},"colorId":0,"depth":0,"index":0},"row":15}],[{"col":8,"gridData":{"color":{"a":0,"b":0,"g":0,"r":0},"colorId":0,"depth":0,"index":0},"row":0},{"col":8,"gridData":{"color":{"a":0,"b":0,"g":0,"r":0},"colorId":0,"depth":0,"index":0},"row":1},{"col":8,"gridData":{"color":{"a":0,"b":0,"g":0,"r":0},"colorId":0,"depth":0,"index":0},"row":2},{"col":8,"gridData":{"color":{"a":0,"b":0,"g":0,"r":0},"colorId":0,"depth":0,"index":0},"row":3},{"col":8,"gridData":{"color":{"a":1,"b":0.8196079,"g":0.7215686,"r":0.6313726},"colorId":5,"depth":2,"index":0},"row":4},{"col":8,"gridData":{"color":{"a":1,"b":0.2078431,"g":0.3019608,"r":0.5686275},"colorId":10,"depth":3,"index":0},"row":5},{"col":8,"gridData":{"color":{"a":1,"b":0.8196079,"g":0.7215686,"r":0.6313726},"colorId":5,"depth":3,"index":0},"row":6},{"col":8,"gridData":{"color":{"a":1,"b":0.8196079,"g":0.7215686,"r":0.6313726},"colorId":5,"depth":3,"index":0},"row":7},{"col":8,"gridData":{"color":{"a":1,"b":0.8196079,"g":0.7215686,"r":0.6313726},"colorId":5,"depth":3,"index":0},"row":8},{"col":8,"gridData":{"color":{"a":1,"b":0.3254902,"g":0.4901961,"r":0.8313726},"colorId":8,"depth":3,"index":0},"row":9},{"col":8,"gridData":{"color":{"a":1,"b":0.5529412,"g":0.7333333,"r":0.9686275},"colorId":9,"depth":4,"index":0},"row":10},{"col":8,"gridData":{"color":{"a":1,"b":0.5529412,"g":0.7333333,"r":0.9686275},"colorId":9,"depth":4,"index":0},"row":11},{"col":8,"gridData":{"color":{"a":1,"b":0.5529412,"g":0.7333333,"r":0.9686275},"colorId":9,"depth":4,"index":0},"row":12},{"col":8,"gridData":{"color":{"a":1,"b":0.2078431,"g":0.3019608,"r":0.5686275},"colorId":10,"depth":4,"index":0},"row":13},{"col":8,"gridData":{"color":{"a":0,"b":0,"g":0,"r":0},"colorId":0,"depth":0,"index":0},"row":14},{"col":8,"gridData":{"color":{"a":0,"b":0,"g":0,"r":0},"colorId":0,"depth":0,"index":0},"row":15}],[{"col":9,"gridData":{"color":{"a":0,"b":0,"g":0,"r":0},"colorId":10,"depth":0,"index":0},"row":0},{"col":9,"gridData":{"color":{"a":1,"b":0.2078431,"g":0.3019608,"r":0.5686275},"colorId":10,"depth":3,"index":0},"row":1},{"col":9,"gridData":{"color":{"a":1,"b":0.8196079,"g":0.7215686,"r":0.6313726},"colorId":5,"depth":2,"index":0},"row":2},{"col":9,"gridData":{"color":{"a":1,"b":0.8196079,"g":0.7215686,"r":0.6313726},"colorId":5,"depth":2,"index":0},"row":3},{"col":9,"gridData":{"color":{"a":1,"b":0.8196079,"g":0.7215686,"r":0.6313726},"colorId":5,"depth":2,"index":0},"row":4},{"col":9,"gridData":{"color":{"a":1,"b":0.2078431,"g":0.3019608,"r":0.5686275},"colorId":10,"depth":3,"index":0},"row":5},{"col":9,"gridData":{"color":{"a":1,"b":0.3333333,"g":0.1647059,"r":0.9137255},"colorId":1,"depth":3,"index":0},"row":6},{"col":9,"gridData":{"color":{"a":1,"b":0.3333333,"g":0.1647059,"r":0.9137255},"colorId":1,"depth":3,"index":0},"row":7},{"col":9,"gridData":{"color":{"a":1,"b":0.3333333,"g":0.1647059,"r":0.9137255},"colorId":1,"depth":3,"index":0},"row":8},{"col":9,"gridData":{"color":{"a":1,"b":0.3333333,"g":0.1647059,"r":0.9137255},"colorId":1,"depth":3,"index":0},"row":9},{"col":9,"gridData":{"color":{"a":1,"b":0.5529412,"g":0.7333333,"r":0.9686275},"colorId":9,"depth":4,"index":0},"row":10},{"col":9,"gridData":{"color":{"a":1,"b":0.5529412,"g":0.7333333,"r":0.9686275},"colorId":9,"depth":4,"index":0},"row":11},{"col":9,"gridData":{"color":{"a":1,"b":0.2078431,"g":0.3019608,"r":0.5686275},"colorId":10,"depth":4,"index":0},"row":12},{"col":9,"gridData":{"color":{"a":1,"b":0.2078431,"g":0.3019608,"r":0.5686275},"colorId":10,"depth":4,"index":0},"row":13},{"col":9,"gridData":{"color":{"a":0,"b":0,"g":0,"r":0},"colorId":0,"depth":0,"index":0},"row":14},{"col":9,"gridData":{"color":{"a":0,"b":0,"g":0,"r":0},"colorId":0,"depth":0,"index":0},"row":15}],[{"col":10,"gridData":{"color":{"a":0,"b":0,"g":0,"r":0},"colorId":0,"depth":0,"index":0},"row":0},{"col":10,"gridData":{"color":{"a":0,"b":0,"g":0,"r":0},"colorId":0,"depth":0,"index":0},"row":1},{"col":10,"gridData":{"color":{"a":0,"b":0,"g":0,"r":0},"colorId":0,"depth":0,"index":0},"row":2},{"col":10,"gridData":{"color":{"a":0,"b":0,"g":0,"r":0},"colorId":9,"depth":0,"index":0},"row":3},{"col":10,"gridData":{"color":{"a":1,"b":0.5529412,"g":0.7333333,"r":0.9686275},"colorId":9,"depth":2,"index":0},"row":4},{"col":10,"gridData":{"color":{"a":1,"b":0.5529412,"g":0.7333333,"r":0.9686275},"colorId":9,"depth":3,"index":0},"row":5},{"col":10,"gridData":{"color":{"a":1,"b":0.2196078,"g":0.04705882,"r":0.572549},"colorId":0,"depth":3,"index":0},"row":6},{"col":10,"gridData":{"color":{"a":1,"b":0.2196078,"g":0.04705882,"r":0.572549},"colorId":0,"depth":3,"index":0},"row":7},{"col":10,"gridData":{"color":{"a":1,"b":0.2196078,"g":0.04705882,"r":0.572549},"colorId":0,"depth":3,"index":0},"row":8},{"col":10,"gridData":{"color":{"a":1,"b":0.2196078,"g":0.04705882,"r":0.572549},"colorId":0,"depth":3,"index":0},"row":9},{"col":10,"gridData":{"color":{"a":0,"b":0,"g":0,"r":0},"colorId":0,"depth":0,"index":0},"row":10},{"col":10,"gridData":{"color":{"a":1,"b":0.3254902,"g":0.4901961,"r":0.8313726},"colorId":8,"depth":1,"index":0},"row":11},{"col":10,"gridData":{"color":{"a":0,"b":0,"g":0,"r":0},"colorId":0,"depth":0,"index":0},"row":12},{"col":10,"gridData":{"color":{"a":0,"b":0,"g":0,"r":0},"colorId":0,"depth":0,"index":0},"row":13},{"col":10,"gridData":{"color":{"a":0,"b":0,"g":0,"r":0},"colorId":0,"depth":0,"index":0},"row":14},{"col":10,"gridData":{"color":{"a":0,"b":0,"g":0,"r":0},"colorId":0,"depth":0,"index":0},"row":15}],[{"col":11,"gridData":{"color":{"a":0,"b":0,"g":0,"r":0},"colorId":0,"depth":0,"index":0},"row":0},{"col":11,"gridData":{"color":{"a":0,"b":0,"g":0,"r":0},"colorId":0,"depth":0,"index":0},"row":1},{"col":11,"gridData":{"color":{"a":0,"b":0,"g":0,"r":0},"colorId":0,"depth":0,"index":0},"row":2},{"col":11,"gridData":{"color":{"a":0,"b":0,"g":0,"r":0},"colorId":9,"depth":0,"index":0},"row":3},{"col":11,"gridData":{"color":{"a":1,"b":0.5529412,"g":0.7333333,"r":0.9686275},"colorId":9,"depth":2,"index":0},"row":4},{"col":11,"gridData":{"color":{"a":1,"b":0.5529412,"g":0.7333333,"r":0.9686275},"colorId":9,"depth":2,"index":0},"row":5},{"col":11,"gridData":{"color":{"a":1,"b":0.2196078,"g":0.04705882,"r":0.572549},"colorId":0,"depth":3,"index":0},"row":6},{"col":11,"gridData":{"color":{"a":1,"b":0.2196078,"g":0.04705882,"r":0.572549},"colorId":0,"depth":3,"index":0},"row":7},{"col":11,"gridData":{"color":{"a":1,"b":0.2196078,"g":0.04705882,"r":0.572549},"colorId":0,"depth":3,"index":0},"row":8},{"col":11,"gridData":{"color":{"a":0,"b":0,"g":0,"r":0},"colorId":0,"depth":0,"index":0},"row":9},{"col":11,"gridData":{"color":{"a":0,"b":0,"g":0,"r":0},"colorId":0,"depth":0,"index":0},"row":10},{"col":11,"gridData":{"color":{"a":0,"b":0,"g":0,"r":0},"colorId":0,"depth":0,"index":0},"row":11},{"col":11,"gridData":{"color":{"a":0,"b":0,"g":0,"r":0},"colorId":0,"depth":0,"index":0},"row":12},{"col":11,"gridData":{"color":{"a":0,"b":0,"g":0,"r":0},"colorId":0,"depth":0,"index":0},"row":13},{"col":11,"gridData":{"color":{"a":0,"b":0,"g":0,"r":0},"colorId":0,"depth":0,"index":0},"row":14},{"col":11,"gridData":{"color":{"a":0,"b":0,"g":0,"r":0},"colorId":0,"depth":0,"index":0},"row":15}],[{"col":12,"gridData":{"color":{"a":0,"b":0,"g":0,"r":0},"colorId":0,"depth":0,"index":0},"row":0},{"col":12,"gridData":{"color":{"a":0,"b":0,"g":0,"r":0},"colorId":0,"depth":0,"index":0},"row":1},{"col":12,"gridData":{"color":{"a":0,"b":0,"g":0,"r":0},"colorId":0,"depth":0,"index":0},"row":2},{"col":12,"gridData":{"color":{"a":0,"b":0,"g":0,"r":0},"colorId":0,"depth":0,"index":0},"row":3},{"col":12,"gridData":{"color":{"a":0,"b":0,"g":0,"r":0},"colorId":0,"depth":0,"index":0},"row":4},{"col":12,"gridData":{"color":{"a":0,"b":0,"g":0,"r":0},"colorId":0,"depth":0,"index":0},"row":5},{"col":12,"gridData":{"color":{"a":0,"b":0,"g":0,"r":0},"colorId":0,"depth":0,"index":0},"row":6},{"col":12,"gridData":{"color":{"a":0,"b":0,"g":0,"r":0},"colorId":0,"depth":0,"index":0},"row":7},{"col":12,"gridData":{"color":{"a":0,"b":0,"g":0,"r":0},"colorId":0,"depth":0,"index":0},"row":8},{"col":12,"gridData":{"color":{"a":0,"b":0,"g":0,"r":0},"colorId":0,"depth":0,"index":0},"row":9},{"col":12,"gridData":{"color":{"a":0,"b":0,"g":0,"r":0},"colorId":0,"depth":0,"index":0},"row":10},{"col":12,"gridData":{"color":{"a":0,"b":0,"g":0,"r":0},"colorId":0,"depth":0,"index":0},"row":11},{"col":12,"gridData":{"color":{"a":0,"b":0,"g":0,"r":0},"colorId":0,"depth":0,"index":0},"row":12},{"col":12,"gridData":{"color":{"a":0,"b":0,"g":0,"r":0},"colorId":0,"depth":0,"index":0},"row":13},{"col":12,"gridData":{"color":{"a":0,"b":0,"g":0,"r":0},"colorId":0,"depth":0,"index":0},"row":14},{"col":12,"gridData":{"color":{"a":0,"b":0,"g":0,"r":0},"colorId":0,"depth":0,"index":0},"row":15}],[{"col":13,"gridData":{"color":{"a":0,"b":0,"g":0,"r":0},"colorId":0,"depth":0,"index":0},"row":0},{"col":13,"gridData":{"color":{"a":0,"b":0,"g":0,"r":0},"colorId":0,"depth":0,"index":0},"row":1},{"col":13,"gridData":{"color":{"a":0,"b":0,"g":0,"r":0},"colorId":0,"depth":0,"index":0},"row":2},{"col":13,"gridData":{"color":{"a":0,"b":0,"g":0,"r":0},"colorId":0,"depth":0,"index":0},"row":3},{"col":13,"gridData":{"color":{"a":0,"b":0,"g":0,"r":0},"colorId":0,"depth":0,"index":0},"row":4},{"col":13,"gridData":{"color":{"a":0,"b":0,"g":0,"r":0},"colorId":0,"depth":0,"index":0},"row":5},{"col":13,"gridData":{"color":{"a":0,"b":0,"g":0,"r":0},"colorId":0,"depth":0,"index":0},"row":6},{"col":13,"gridData":{"color":{"a":0,"b":0,"g":0,"r":0},"colorId":0,"depth":0,"index":0},"row":7},{"col":13,"gridData":{"color":{"a":0,"b":0,"g":0,"r":0},"colorId":0,"depth":0,"index":0},"row":8},{"col":13,"gridData":{"color":{"a":0,"b":0,"g":0,"r":0},"colorId":0,"depth":0,"index":0},"row":9},{"col":13,"gridData":{"color":{"a":0,"b":0,"g":0,"r":0},"colorId":0,"depth":0,"index":0},"row":10},{"col":13,"gridData":{"color":{"a":0,"b":0,"g":0,"r":0},"colorId":0,"depth":0,"index":0},"row":11},{"col":13,"gridData":{"color":{"a":0,"b":0,"g":0,"r":0},"colorId":0,"depth":0,"index":0},"row":12},{"col":13,"gridData":{"color":{"a":0,"b":0,"g":0,"r":0},"colorId":0,"depth":0,"index":0},"row":13},{"col":13,"gridData":{"color":{"a":0,"b":0,"g":0,"r":0},"colorId":0,"depth":0,"index":0},"row":14},{"col":13,"gridData":{"color":{"a":0,"b":0,"g":0,"r":0},"colorId":0,"depth":0,"index":0},"row":15}],[{"col":14,"gridData":{"color":{"a":0,"b":0,"g":0,"r":0},"colorId":0,"depth":0,"index":0},"row":0},{"col":14,"gridData":{"color":{"a":0,"b":0,"g":0,"r":0},"colorId":0,"depth":0,"index":0},"row":1},{"col":14,"gridData":{"color":{"a":0,"b":0,"g":0,"r":0},"colorId":0,"depth":0,"index":0},"row":2},{"col":14,"gridData":{"color":{"a":0,"b":0,"g":0,"r":0},"colorId":0,"depth":0,"index":0},"row":3},{"col":14,"gridData":{"color":{"a":0,"b":0,"g":0,"r":0},"colorId":0,"depth":0,"index":0},"row":4},{"col":14,"gridData":{"color":{"a":0,"b":0,"g":0,"r":0},"colorId":0,"depth":0,"index":0},"row":5},{"col":14,"gridData":{"color":{"a":0,"b":0,"g":0,"r":0},"colorId":0,"depth":0,"index":0},"row":6},{"col":14,"gridData":{"color":{"a":0,"b":0,"g":0,"r":0},"colorId":0,"depth":0,"index":0},"row":7},{"col":14,"gridData":{"color":{"a":0,"b":0,"g":0,"r":0},"colorId":0,"depth":0,"index":0},"row":8},{"col":14,"gridData":{"color":{"a":0,"b":0,"g":0,"r":0},"colorId":0,"depth":0,"index":0},"row":9},{"col":14,"gridData":{"color":{"a":0,"b":0,"g":0,"r":0},"colorId":0,"depth":0,"index":0},"row":10},{"col":14,"gridData":{"color":{"a":0,"b":0,"g":0,"r":0},"colorId":0,"depth":0,"index":0},"row":11},{"col":14,"gridData":{"color":{"a":0,"b":0,"g":0,"r":0},"colorId":0,"depth":0,"index":0},"row":12},{"col":14,"gridData":{"color":{"a":0,"b":0,"g":0,"r":0},"colorId":0,"depth":0,"index":0},"row":13},{"col":14,"gridData":{"color":{"a":0,"b":0,"g":0,"r":0},"colorId":0,"depth":0,"index":0},"row":14},{"col":14,"gridData":{"color":{"a":0,"b":0,"g":0,"r":0},"colorId":0,"depth":0,"index":0},"row":15}],[{"col":15,"gridData":{"color":{"a":0,"b":0,"g":0,"r":0},"colorId":0,"depth":0,"index":0},"row":0},{"col":15,"gridData":{"color":{"a":0,"b":0,"g":0,"r":0},"colorId":0,"depth":0,"index":0},"row":1},{"col":15,"gridData":{"color":{"a":0,"b":0,"g":0,"r":0},"colorId":0,"depth":0,"index":0},"row":2},{"col":15,"gridData":{"color":{"a":0,"b":0,"g":0,"r":0},"colorId":0,"depth":0,"index":0},"row":3},{"col":15,"gridData":{"color":{"a":0,"b":0,"g":0,"r":0},"colorId":0,"depth":0,"index":0},"row":4},{"col":15,"gridData":{"color":{"a":0,"b":0,"g":0,"r":0},"colorId":0,"depth":0,"index":0},"row":5},{"col":15,"gridData":{"color":{"a":0,"b":0,"g":0,"r":0},"colorId":0,"depth":0,"index":0},"row":6},{"col":15,"gridData":{"color":{"a":0,"b":0,"g":0,"r":0},"colorId":0,"depth":0,"index":0},"row":7},{"col":15,"gridData":{"color":{"a":0,"b":0,"g":0,"r":0},"colorId":0,"depth":0,"index":0},"row":8},{"col":15,"gridData":{"color":{"a":0,"b":0,"g":0,"r":0},"colorId":0,"depth":0,"index":0},"row":9},{"col":15,"gridData":{"color":{"a":0,"b":0,"g":0,"r":0},"colorId":0,"depth":0,"index":0},"row":10},{"col":15,"gridData":{"color":{"a":0,"b":0,"g":0,"r":0},"colorId":0,"depth":0,"index":0},"row":11},{"col":15,"gridData":{"color":{"a":0,"b":0,"g":0,"r":0},"colorId":0,"depth":0,"index":0},"row":12},{"col":15,"gridData":{"color":{"a":0,"b":0,"g":0,"r":0},"colorId":0,"depth":0,"index":0},"row":13},{"col":15,"gridData":{"color":{"a":0,"b":0,"g":0,"r":0},"colorId":0,"depth":0,"index":0},"row":14},{"col":15,"gridData":{"color":{"a":0,"b":0,"g":0,"r":0},"colorId":0,"depth":0,"index":0},"row":15}]],"shapeName":"TestJson"}